batchkit/client.py
test_repo-0.0.0.1.dist-info/METADATA
test_repo-0.0.0.1.dist-info/WHEEL
test_repo-0.0.0.1.dist-info/top_level.txt
test_repo-0.0.0.1.dist-info/RECORD
