Metadata-Version: 2.1
Name: test-repo
Version: 0.0.0.1
Summary: None
Home-page: https://github.com/JoshBClemons/test_repo
Author: Josh Clemons
Author-email: clemonsjoshua6@microsoft.com
License: MIT
Platform: UNKNOWN
Classifier: Programming Language :: Python :: 3
Classifier: License :: OSI Approved :: MIT License
Classifier: Operating System :: POSIX :: Linux
Requires-Python: >=3.6
Requires-Dist: requests (>=2.23.0)
